ppsetuptools/__init__.py
ppsetuptools/ppsetuptools.py
ppsetuptools-2.0.2.dist-info/LICENSE
ppsetuptools-2.0.2.dist-info/METADATA
ppsetuptools-2.0.2.dist-info/WHEEL
ppsetuptools-2.0.2.dist-info/top_level.txt
ppsetuptools-2.0.2.dist-info/RECORD
