Metadata-Version: 2.1
Name: ppsetuptools
Version: 2.0.2
Summary: Drop in replacement for setuptools that uses pyproject.toml files
Home-page: UNKNOWN
Author-email: Adam Weeden <adamweeden@gmail.com>
License: UNKNOWN
Project-URL: repository, https://github.com/TheCleric/ppsetuptools
Keywords: setuptools,pyproject,setup.py,pyproject.toml,replacement,pep621,pep-621
Platform: UNKNOWN
Classifier: Development Status :: 4 - Beta
Classifier: Intended Audience :: Developers
Classifier: Topic :: Software Development :: Libraries
Classifier: License :: OSI Approved :: MIT License
Classifier: Programming Language :: Python :: 3
Classifier: Programming Language :: Python :: 3.6
Classifier: Programming Language :: Python :: 3.7
Classifier: Programming Language :: Python :: 3.8
Requires-Python: >=3.6
Requires-Dist: setuptools (>=38.6.0)
Requires-Dist: toml
Provides-Extra: dev
Requires-Dist: autopep8 ; extra == 'dev'
Requires-Dist: isort ; extra == 'dev'
Requires-Dist: pre-commit ; extra == 'dev'
Requires-Dist: setuptools ; extra == 'dev'
Requires-Dist: twine ; extra == 'dev'
Requires-Dist: upgrade-ensurepip ; extra == 'dev'
Requires-Dist: wheel ; extra == 'dev'
Provides-Extra: test
Requires-Dist: mypy ; extra == 'test'
Requires-Dist: pydantic ; extra == 'test'
Requires-Dist: pylint ; extra == 'test'
Requires-Dist: pytest ; extra == 'test'
Requires-Dist: pytest-cov ; extra == 'test'
